scButterfly/__init__.py
scButterfly/butterfly.py
scButterfly/calculate_cluster.py
scButterfly/data_processing.py
scButterfly/draw_cluster.py
scButterfly/logger.py
scButterfly/model_component.py
scButterfly/model_utlis.py
scButterfly/split_datasets.py
scButterfly/train_model.py
scButterfly/train_model_cite.py
scButterfly/train_model_cite_background.py
scButterfly/train_model_perturb.py
scButterfly/version.py
scButterfly-0.0.9.dist-info/LICENSE
scButterfly-0.0.9.dist-info/METADATA
scButterfly-0.0.9.dist-info/WHEEL
scButterfly-0.0.9.dist-info/top_level.txt
scButterfly-0.0.9.dist-info/RECORD
