Metadata-Version: 2.1
Name: scButterfly
Version: 0.0.9
Summary: A versatile single-cell cross-modality translation method via dual-aligned variational autoencoders
Home-page: https://github.com/BioX-NKU/scButterfly
Author: BioX-NKU
License: MIT Licence
Keywords: single cell,cross-modality translation,dual-aligned variational autoencoder
Classifier: Programming Language :: Python :: 3.9
Requires-Python: >=3.9
License-File: LICENSE
Requires-Dist: scanpy >=1.9.1
Requires-Dist: torch >=1.12.1
Requires-Dist: torchvision >=0.13.1
Requires-Dist: torchaudio >=0.12.1
Requires-Dist: scikit-learn >=1.1.3
Requires-Dist: scvi-tools ==0.19.0
Requires-Dist: scvi-colab
Requires-Dist: scipy ==1.9.3
Requires-Dist: episcanpy ==0.3.2
Requires-Dist: seaborn >=0.11.2
Requires-Dist: matplotlib >=3.6.2
Requires-Dist: pot ==0.9.0
Requires-Dist: torchmetrics >=0.11.4
Requires-Dist: leidenalg
Requires-Dist: pybedtools
Requires-Dist: adjusttext
Requires-Dist: jupyter
